myass/__init__.py
myass/assistant.py
myass/cli.py
myass/config.py
myass/config_default.yaml
myass/history.py
myass-0.1.6.dist-info/entry_points.txt
myass-0.1.6.dist-info/LICENSE
myass-0.1.6.dist-info/WHEEL
myass-0.1.6.dist-info/METADATA
myass-0.1.6.dist-info/RECORD
