Metadata-Version: 2.1
Name: myass
Version: 0.1.6
Summary: myass
Author-email: Chris Coleman <chris@chriscoleman.uk>
Classifier: License :: OSI Approved :: MIT License
Requires-Dist: appdirs
Requires-Dist: click
Requires-Dist: oaix
